arhmm/__init__.py
arhmm/core.py
arhmm/dataset.py
arhmm/phase_estimator.py
arhmm/propagator.py
arhmm/py.typed
arhmm/utils.py
arhmm-0.0.5.dist-info/METADATA
arhmm-0.0.5.dist-info/WHEEL
arhmm-0.0.5.dist-info/top_level.txt
arhmm-0.0.5.dist-info/RECORD
